{
    "dom": "Sankey-Chart",
        "width":    960, 
        "height":    500, 
        "data": {
                "source":["Ohne",		"LDP",	"EVP",	"SP",		"GB",	"GLP",	"SVP"],
                "target":["Wirz, Lea","Wirz, Lea","Wirz, Lea","Wirz, Lea","Wirz, Lea","Wirz, Lea","Wirz, Lea"
                ],
                "value": [243	,		8,	6,	395,		1182,	43,	3
                ]
        },
        "nodeWidth":     15,
        "nodePadding":     10,
        "layout":     32,
        "id": "main", 
        "units" : "Stimmen"
        }